LICENSE
MANIFEST.in
README.md
landing-page.md
requirements.txt
setup.py
odata_pretty_printer/__init__.py
odata_pretty_printer/_version.py
odata_pretty_printer/command_line.py
odata_pretty_printer/odata_tools.py
odata_pretty_printer.egg-info/PKG-INFO
odata_pretty_printer.egg-info/SOURCES.txt
odata_pretty_printer.egg-info/dependency_links.txt
odata_pretty_printer.egg-info/entry_points.txt
odata_pretty_printer.egg-info/requires.txt
odata_pretty_printer.egg-info/top_level.txt
tests/pprinter/__init__.py
tests/pprinter/test_odata_parser.py
tests/pprinter/test_odata_pretty_printer.py