Metadata-Version: 2.1
Name: odata-pretty-printer
Version: 0.1.1
Summary: Pretty printer for OData filter expressions
Home-page: https://github.com/stevej2608/oppen-pretty-printer
Author: Steve Jones
Author-email: jonesst608@gmail.com
License: MIT
Platform: UNKNOWN
Classifier: Development Status :: 2 - Pre-Alpha
Classifier: License :: OSI Approved :: MIT License
Classifier: Programming Language :: Python
Classifier: Programming Language :: Python :: 3.6
Classifier: Programming Language :: Python :: 3.7
Classifier: Programming Language :: Python :: 3.8
